evomaster_client/__init__.py
evomaster_client/cli.py
evomaster_client/em_test_utils.py
evomaster_client/controller/__init__.py
evomaster_client/controller/em_app.py
evomaster_client/controller/em_controller.py
evomaster_client/controller/flask_handler.py
evomaster_client/controller/sut_handler.py
evomaster_client/instrumentation/__init__.py
evomaster_client/instrumentation/ast_transformer.py
evomaster_client/instrumentation/import_hook.py
evomaster_client/instrumentation/injected_functions.py
evomaster_client/instrumentation/util.py
evomaster_client/instrumentation/heuristic/__init__.py
evomaster_client/instrumentation/heuristic/heuristics.py
evomaster_client/instrumentation/heuristic/truthness.py
evomaster_client/instrumentation/shared/__init__.py
evomaster_client/instrumentation/shared/objective_naming.py
evomaster_client/instrumentation/staticstate/__init__.py
evomaster_client/instrumentation/staticstate/execution_tracer.py
evomaster_client/instrumentation/staticstate/objective_recorder.py
evomaster_client-0.0.8.dist-info/LICENSE
evomaster_client-0.0.8.dist-info/METADATA
evomaster_client-0.0.8.dist-info/WHEEL
evomaster_client-0.0.8.dist-info/top_level.txt
evomaster_client-0.0.8.dist-info/RECORD
