Metadata-Version: 2.1
Name: evomaster-client
Version: 0.0.8
Summary: EvoMaster client for Python Flask RESTful applications
Home-page: https://github.com/axelmaddonni/EvoMaster
Author: Axel Maddonni
Author-email: axel.maddonni@gmail.com
License: UNKNOWN
Platform: UNKNOWN
Classifier: Programming Language :: Python :: 3
Classifier: License :: OSI Approved :: MIT License
Classifier: Operating System :: OS Independent
Classifier: Development Status :: 4 - Beta
Classifier: Framework :: Flask
Classifier: Topic :: Software Development :: Testing
Requires-Python: >=3.6
License-File: LICENSE
Requires-Dist: astor (==0.8.1)
Requires-Dist: Flask (==2.1.1)
Requires-Dist: gevent (==21.12.0)
